README.rst
setup.py
vrpwrp/__init__.py
vrpwrp.egg-info/PKG-INFO
vrpwrp.egg-info/SOURCES.txt
vrpwrp.egg-info/dependency_links.txt
vrpwrp.egg-info/not-zip-safe
vrpwrp.egg-info/requires.txt
vrpwrp.egg-info/top_level.txt
vrpwrp/config/__init__.py
vrpwrp/config/config.py
vrpwrp/helpers/__init__.py
vrpwrp/helpers/image_helper.py
vrpwrp/tests/__init__.py
vrpwrp/tests/test_boundingbox.py
vrpwrp/tests/test_embedding.py
vrpwrp/tests/test_face_detection.py
vrpwrp/tests/test_face_recognition.py
vrpwrp/tests/test_image_helper.py
vrpwrp/tools/__init__.py
vrpwrp/tools/boundingbox.py
vrpwrp/tools/embedding.py
vrpwrp/wrappers/APIWrapper.py
vrpwrp/wrappers/__init__.py
vrpwrp/wrappers/face_bundle.py
vrpwrp/wrappers/face_detection.py
vrpwrp/wrappers/face_recognition.py
vrpwrp/wrappers/porn_classification.py