Metadata-Version: 1.0
Name: vrpwrp
Version: 0.0.4
Summary: Vision-algorithms Requests Processing Wrappers for deep-learning Computer Vision algorithms on the cloud.
Home-page: http://github.com/ipazc/vrpwrp
Author: Iván de Paz Centeno
Author-email: ipazc@unileon.es
License: MIT
Keywords: vrpwrp face_detection face_recognition face deep-learning computer vision face detection face recognition api rest wrapper
Platform: UNKNOWN
